balto/__init__.py
balto/_logging.py
balto/cli.py
balto/config.py
balto/displayer/__init__.py
balto/displayer/cli_simple.py
balto/displayer/curses.py
balto/displayer/curses_widgets.py
balto/editor.py
balto/event_emitter.py
balto/exceptions.py
balto/interfaces/__init__.py
balto/interfaces/curses/__init__.py
balto/models.py
balto/new_server.py
balto/runners/__init__.py
balto/runners/base.py
balto/runners/docker_runner.py
balto/runners/subprocess_runner.py
balto/start.py
balto/store.py
balto/suite.py
balto/web_interfaces/balto_react/build/asset-manifest.json
balto/web_interfaces/balto_react/build/favicon.ico
balto/web_interfaces/balto_react/build/index.html
balto/web_interfaces/balto_react/build/manifest.json
balto/web_interfaces/balto_react/build/precache-manifest.a568e7b917e6e3e327feaef790d42cf5.js
balto/web_interfaces/balto_react/build/service-worker.js
balto/web_interfaces/balto_react/build/static/css/2.e250451c.chunk.css
balto/web_interfaces/balto_react/build/static/css/2.e250451c.chunk.css.map
balto/web_interfaces/balto_react/build/static/css/main.d303c0cb.chunk.css
balto/web_interfaces/balto_react/build/static/css/main.d303c0cb.chunk.css.map
balto/web_interfaces/balto_react/build/static/js/2.f41e5c85.chunk.js
balto/web_interfaces/balto_react/build/static/js/2.f41e5c85.chunk.js.LICENSE.txt
balto/web_interfaces/balto_react/build/static/js/2.f41e5c85.chunk.js.map
balto/web_interfaces/balto_react/build/static/js/main.980669db.chunk.js
balto/web_interfaces/balto_react/build/static/js/main.980669db.chunk.js.map
balto/web_interfaces/balto_react/build/static/js/runtime-main.471c5276.js
balto/web_interfaces/balto_react/build/static/js/runtime-main.471c5276.js.map
balto-0.3.0.dist-info/entry_points.txt
balto-0.3.0.dist-info/LICENSE
balto-0.3.0.dist-info/WHEEL
balto-0.3.0.dist-info/METADATA
balto-0.3.0.dist-info/RECORD
